mixbaba/__init__.py
mixbaba/beta_utils.py
mixbaba/inputs.py
mixbaba/mixbaba_utils.py
mixbaba/output_utils.py
mixbaba-0.1.1.data/scripts/mixbaba
mixbaba-0.1.1.dist-info/LICENSE.md
mixbaba-0.1.1.dist-info/METADATA
mixbaba-0.1.1.dist-info/WHEEL
mixbaba-0.1.1.dist-info/top_level.txt
mixbaba-0.1.1.dist-info/RECORD
