Metadata-Version: 2.1
Name: mixbaba
Version: 0.1.1
Summary: A tool to analyze AB tests data from Mixpanel funnels
Home-page: UNKNOWN
Author: Vincenzo Lavorini
Author-email: vincenzo.lavorini@naturalcycles.com
License: UNKNOWN
Platform: UNKNOWN
Classifier: Development Status :: 3 - Alpha
Classifier: Environment :: Console
Classifier: Intended Audience :: Developers
Classifier: Natural Language :: English
Classifier: Programming Language :: Python :: 3
Classifier: Operating System :: OS Independent
Classifier: Topic :: Utilities
Requires-Python: >=3.6
Requires-Dist: numpy
Requires-Dist: pandas
Requires-Dist: numba
Requires-Dist: matplotlib
Requires-Dist: scipy
Requires-Dist: tqdm
Requires-Dist: tabulate
